nose_runnable_test_names.py
setup.py
nose_runnable_test_names.egg-info/PKG-INFO
nose_runnable_test_names.egg-info/SOURCES.txt
nose_runnable_test_names.egg-info/dependency_links.txt
nose_runnable_test_names.egg-info/entry_points.txt
nose_runnable_test_names.egg-info/requires.txt
nose_runnable_test_names.egg-info/top_level.txt