Metadata-Version: 1.1
Name: nose-runnable-test-names
Version: 0.1
Summary: Changes the nose test descriptions so that you can copy and paste a test to the nose runner
Home-page: https://github.com/coldeasy/nose-runnable-test-names
Author: Colin Deasy
Author-email: coldeasy+nose@gmail.com
License: UNKNOWN
Keywords: nose,test,plugins
Platform: UNKNOWN
Classifier: Development Status :: 5 - Production/Stable
Classifier: Intended Audience :: Developers
Classifier: License :: OSI Approved :: MIT License
Classifier: Natural Language :: English
Classifier: Programming Language :: Python
Classifier: Topic :: Software Development :: Testing
